unit_scaling/__init__.py
unit_scaling/_internal_utils.py
unit_scaling/_modules.py
unit_scaling/_version.py
unit_scaling/analysis.py
unit_scaling/constraints.py
unit_scaling/docs.py
unit_scaling/formats.py
unit_scaling/functional.py
unit_scaling/optim.py
unit_scaling/parameter.py
unit_scaling/scale.py
unit_scaling/utils.py
unit_scaling/core/__init__.py
unit_scaling/core/functional.py
unit_scaling/tests/__init__.py
unit_scaling/tests/conftest.py
unit_scaling/tests/helper.py
unit_scaling/tests/test_analysis.py
unit_scaling/tests/test_constraints.py
unit_scaling/tests/test_docs.py
unit_scaling/tests/test_formats.py
unit_scaling/tests/test_functional.py
unit_scaling/tests/test_modules.py
unit_scaling/tests/test_optim.py
unit_scaling/tests/test_parameter.py
unit_scaling/tests/test_scale.py
unit_scaling/tests/test_utils.py
unit_scaling/tests/core/__init__.py
unit_scaling/tests/core/test_functional.py
unit_scaling/tests/transforms/__init__.py
unit_scaling/tests/transforms/test_compile.py
unit_scaling/tests/transforms/test_simulate_format.py
unit_scaling/tests/transforms/test_track_scales.py
unit_scaling/tests/transforms/test_unit_scale.py
unit_scaling/transforms/__init__.py
unit_scaling/transforms/_compile.py
unit_scaling/transforms/_simulate_format.py
unit_scaling/transforms/_track_scales.py
unit_scaling/transforms/_unit_scale.py
unit_scaling/transforms/utils.py
unit_scaling-0.3.5.dist-info/licenses/LICENSE
unit_scaling-0.3.5.dist-info/licenses/NOTICE.md
unit_scaling-0.3.5.dist-info/METADATA
unit_scaling-0.3.5.dist-info/WHEEL
unit_scaling-0.3.5.dist-info/top_level.txt
unit_scaling-0.3.5.dist-info/RECORD
