Metadata-Version: 2.4
Name: unit-scaling
Version: 0.3.5
Summary: A library for unit scaling in PyTorch, based on the paper 'u-muP: The Unit-Scaled Maximal Update Parametrization.'
Author-email: Charlie Blake <charlieb@graphcore.ai>, Douglas Orr <douglaso@graphcore.ai>
Project-URL: Homepage, https://github.com/graphcore-research/unit-scaling/#readme
Project-URL: Bug Reports, https://github.com/graphcore-research/unit-scaling/issues
Project-URL: Source, https://github.com/graphcore-research/unit-scaling/
Classifier: Development Status :: 4 - Beta
Classifier: Intended Audience :: Developers
Classifier: Intended Audience :: Science/Research
Classifier: License :: OSI Approved :: Apache Software License
Classifier: Programming Language :: Python :: 3.9
Classifier: Programming Language :: Python :: 3.10
Classifier: Programming Language :: Python :: 3.11
Classifier: Programming Language :: Python :: 3.12
Classifier: Programming Language :: Python :: 3.13
Classifier: Programming Language :: Python :: 3.14
Classifier: Topic :: Scientific/Engineering :: Artificial Intelligence
Requires-Python: >=3.9
License-File: LICENSE
License-File: NOTICE.md
Requires-Dist: docstring-parser
Requires-Dist: einops
Requires-Dist: tabulate
Requires-Dist: torch>=2.2
Provides-Extra: dev
Requires-Dist: check-manifest; extra == "dev"
Provides-Extra: test
Requires-Dist: pytest; extra == "test"
Provides-Extra: analysis
Requires-Dist: datasets; extra == "analysis"
Requires-Dist: matplotlib; extra == "analysis"
Requires-Dist: pandas; extra == "analysis"
Requires-Dist: seaborn; extra == "analysis"
Dynamic: license-file
